wisdoms_dapr/__init__.py
wisdoms_dapr/config.py
wisdoms_dapr/consts.py
wisdoms_dapr/exceptions.py
wisdoms_dapr/logger.py
wisdoms_dapr/redis.py
wisdoms_dapr/types.py
wisdoms_dapr/common/__init__.py
wisdoms_dapr/common/enforce.py
wisdoms_dapr/common/service_register.py
wisdoms_dapr/data/__init__.py
wisdoms_dapr/data/data.py
wisdoms_dapr/deps/__init__.py
wisdoms_dapr/deps/common.py
wisdoms_dapr/deps/schedule.py
wisdoms_dapr/elasticsearch/__init__.py
wisdoms_dapr/elasticsearch/connection.py
wisdoms_dapr/elasticsearch/document.py
wisdoms_dapr/elasticsearch/searches.py
wisdoms_dapr/models/__init__.py
wisdoms_dapr/models/es/__init__.py
wisdoms_dapr/models/es/share.py
wisdoms_dapr/schemas/__init__.py
wisdoms_dapr/schemas/base.py
wisdoms_dapr/schemas/share.py
wisdoms_dapr-0.4.2.dist-info/LICENSE
wisdoms_dapr-0.4.2.dist-info/METADATA
wisdoms_dapr-0.4.2.dist-info/WHEEL
wisdoms_dapr-0.4.2.dist-info/top_level.txt
wisdoms_dapr-0.4.2.dist-info/RECORD
