Metadata-Version: 2.1
Name: wisdoms-dapr
Version: 0.4.2
Summary: wisdoms dapr package
Home-page: https://github.com/li1234yun/nameko-wrapper
Author: li1234yun
Author-email: li1234yun@163.com
Classifier: Programming Language :: Python :: 3.9
Classifier: License :: OSI Approved :: MIT License
Classifier: Operating System :: OS Independent
Requires-Python: >=3.9
License-File: LICENSE
Requires-Dist: elasticsearch-dsl
Requires-Dist: redis
Requires-Dist: dapr-ext-fastapi
